_naay_native/__init__.py
_naay_native/_naay_native.cpython-313-darwin.so
_naay_pure/__init__.py
_naay_pure/parser.py
naay-2025.12.8.post2.dist-info/METADATA
naay-2025.12.8.post2.dist-info/WHEEL
naay-2025.12.8.post2.dist-info/licenses/LICENSE
naay/__init__.py
naay/py.typed
naay-2025.12.8.post2.dist-info/RECORD
