Metadata-Version: 2.4
Name: naay
Version: 2025.12.8.post2
Classifier: Programming Language :: Python :: 3
Classifier: Programming Language :: Python :: 3 :: Only
Classifier: Programming Language :: Python :: 3.13
Classifier: Programming Language :: Python :: Implementation :: CPython
Classifier: Programming Language :: Python :: Implementation :: PyPy
Classifier: Operating System :: Microsoft :: Windows
Classifier: Operating System :: POSIX :: Linux
Classifier: Operating System :: MacOS :: MacOS X
Requires-Dist: maturin>=1.10.2 ; extra == 'dev'
Requires-Dist: ruamel-yaml>=0.18 ; extra == 'dev'
Requires-Dist: pyyaml>=6 ; extra == 'dev'
Requires-Dist: rust-just>=1.43.1 ; extra == 'dev'
Requires-Dist: types-pyyaml>=6.0.12.20250915 ; extra == 'dev'
Requires-Dist: mypy>=1.19.0 ; extra == 'dev'
Requires-Dist: pytest>=8.3 ; extra == 'dev'
Requires-Dist: prek>=0.2.20 ; extra == 'dev'
Requires-Dist: radon>=6.0.1 ; extra == 'dev'
Requires-Dist: skylos>=2.5.3 ; extra == 'dev'
Requires-Dist: pytest-cov>=7.0.0 ; extra == 'dev'
Requires-Dist: ruff>=0.14.8 ; extra == 'dev'
Requires-Dist: basedpyright>=1.35.0 ; extra == 'dev'
Requires-Dist: beartype>=0.22.8 ; extra == 'beartype'
Provides-Extra: dev
Provides-Extra: beartype
License-File: LICENSE
Summary: A fast YAML subset parser/dumper for Python powered by Rust
Home-Page: https://github.com/rbroderi/naay
Author-email: rbroderi <richard.broderick@gmail.com>
License: LGPL-3.0-or-later
Requires-Python: >=3.13
